pvt/__init__.py
pvt/copy.py
pvt/delete.py
pvt/find.py
pvt/list.py
pvt/new.py
pvt/read.py
permanent_variable_tool-1.0.5.dist-info/LICENSE
permanent_variable_tool-1.0.5.dist-info/METADATA
permanent_variable_tool-1.0.5.dist-info/WHEEL
permanent_variable_tool-1.0.5.dist-info/top_level.txt
permanent_variable_tool-1.0.5.dist-info/RECORD
